{
  "version": 1,
  "width": 80,
  "height": 24,
  "duration": 68.564664,
  "command": "/bin/bash",
  "title": "more demo",
  "env": {
    "TERM": "xterm-256color",
    "SHELL": "/bin/bash"
  },
  "stdout": [
    [
      0.128819,
      "\u001b]0;grossp@localhost:~\u0007\u001b[?1034h[grossp@~ ]\u003e "
    ],
    [
      0.502203,
      "#"
    ],
    [
      0.272163,
      "m"
    ],
    [
      0.159955,
      "o"
    ],
    [
      0.040062,
      "r"
    ],
    [
      0.063935,
      "e"
    ],
    [
      0.112007,
      " "
    ],
    [
      0.119989,
      "i"
    ],
    [
      0.103956,
      "s"
    ],
    [
      0.080041,
      " "
    ],
    [
      0.120004,
      "l"
    ],
    [
      0.167871,
      "i"
    ],
    [
      0.184072,
      "k"
    ],
    [
      0.079893,
      "e"
    ],
    [
      0.095750,
      " "
    ],
    [
      0.079980,
      "l"
    ],
    [
      0.080350,
      "e"
    ],
    [
      0.216014,
      "s"
    ],
    [
      0.144019,
      "s"
    ],
    [
      0.064036,
      ","
    ],
    [
      0.047979,
      " "
    ],
    [
      0.087803,
      "b"
    ],
    [
      0.080204,
      "u"
    ],
    [
      0.103931,
      "t"
    ],
    [
      0.064017,
      " "
    ],
    [
      0.095805,
      "l"
    ],
    [
      0.103912,
      "e"
    ],
    [
      0.488261,
      "s"
    ],
    [
      0.167954,
      "s"
    ],
    [
      0.144014,
      " "
    ],
    [
      0.328021,
      "p"
    ],
    [
      0.175845,
      "o"
    ],
    [
      0.088099,
      "w"
    ],
    [
      0.127983,
      "e"
    ],
    [
      0.096001,
      "r"
    ],
    [
      0.520004,
      "f"
    ],
    [
      0.119962,
      "u"
    ],
    [
      0.232007,
      "l"
    ],
    [
      0.375985,
      "."
    ],
    [
      0.680476,
      "\r\n\u001b]0;grossp@localhost:~\u0007[grossp@~ ]\u003e "
    ],
    [
      0.351203,
      "#"
    ],
    [
      1.200171,
      "I"
    ],
    [
      0.655785,
      "\u0008\u001b[K"
    ],
    [
      0.216129,
      "m"
    ],
    [
      0.167996,
      "o"
    ],
    [
      0.279954,
      "r"
    ],
    [
      0.111971,
      "e"
    ],
    [
      0.120002,
      " "
    ],
    [
      0.080017,
      "o"
    ],
    [
      0.087838,
      "n"
    ],
    [
      0.144073,
      "l"
    ],
    [
      0.192090,
      "y"
    ],
    [
      0.087834,
      " "
    ],
    [
      0.200145,
      "l"
    ],
    [
      0.143976,
      "e"
    ],
    [
      0.128001,
      "t"
    ],
    [
      0.176044,
      "s"
    ],
    [
      0.127986,
      " "
    ],
    [
      0.087946,
      "y"
    ],
    [
      0.080047,
      "o"
    ],
    [
      0.087956,
      "u"
    ],
    [
      0.087987,
      " "
    ],
    [
      0.191975,
      "m"
    ],
    [
      0.159987,
      "o"
    ],
    [
      0.127839,
      "v"
    ],
    [
      0.152145,
      "e"
    ],
    [
      0.103989,
      " "
    ],
    [
      0.103996,
      "d"
    ],
    [
      0.055854,
      "o"
    ],
    [
      0.152174,
      "w"
    ],
    [
      0.079928,
      "n"
    ],
    [
      0.464073,
      " "
    ],
    [
      0.127950,
      "i"
    ],
    [
      0.079971,
      "n"
    ],
    [
      0.072044,
      " "
    ],
    [
      0.152072,
      "a"
    ],
    [
      0.063875,
      " "
    ],
    [
      0.359895,
      "f"
    ],
    [
      0.064076,
      "i"
    ],
    [
      0.232066,
      "l"
    ],
    [
      0.183913,
      "e"
    ],
    [
      1.535710,
      " "
    ],
    [
      0.088210,
      "a"
    ],
    [
      0.143985,
      "n"
    ],
    [
      0.047981,
      "d"
    ],
    [
      0.112010,
      " "
    ],
    [
      0.192144,
      "o"
    ],
    [
      0.079867,
      "n"
    ],
    [
      0.087958,
      "c"
    ],
    [
      0.087963,
      "e"
    ],
    [
      0.095892,
      " "
    ],
    [
      0.127825,
      "y"
    ],
    [
      0.040317,
      "o"
    ],
    [
      0.080010,
      "u"
    ],
    [
      0.095972,
      " "
    ],
    [
      0.095981,
      "r"
    ],
    [
      0.080033,
      "e"
    ],
    [
      0.239970,
      "a"
    ],
    [
      0.191984,
      "c"
    ],
    [
      0.279847,
      "h"
    ],
    [
      0.328535,
      "\r\n\u001b]0;grossp@localhost:~\u0007[grossp@~ ]\u003e "
    ],
    [
      0.215534,
      "#"
    ],
    [
      0.215978,
      "t"
    ],
    [
      0.095912,
      "h"
    ],
    [
      0.120075,
      "e"
    ],
    [
      0.103988,
      " "
    ],
    [
      0.184058,
      "e"
    ],
    [
      0.111732,
      "n"
    ],
    [
      0.080200,
      "d"
    ],
    [
      0.111860,
      " "
    ],
    [
      0.040172,
      "i"
    ],
    [
      0.103958,
      "t"
    ],
    [
      0.143907,
      " "
    ],
    [
      0.312089,
      "e"
    ],
    [
      0.239899,
      "x"
    ],
    [
      0.168077,
      "i"
    ],
    [
      0.120006,
      "t"
    ],
    [
      0.167882,
      "s"
    ],
    [
      0.256093,
      "."
    ],
    [
      0.672395,
      "\r\n\u001b]0;grossp@localhost:~\u0007[grossp@~ ]\u003e "
    ],
    [
      1.271521,
      "m"
    ],
    [
      0.143974,
      "o"
    ],
    [
      0.103983,
      "r"
    ],
    [
      0.055984,
      "e"
    ],
    [
      0.048019,
      " "
    ],
    [
      0.207967,
      "/"
    ],
    [
      0.079993,
      "e"
    ],
    [
      0.104030,
      "t"
    ],
    [
      0.351974,
      "c"
    ],
    [
      0.495960,
      "/"
    ],
    [
      0.327978,
      "y"
    ],
    [
      0.231982,
      "u"
    ],
    [
      0.223992,
      "m"
    ],
    [
      0.215993,
      "."
    ],
    [
      0.207890,
      "c"
    ],
    [
      0.152103,
      "o"
    ],
    [
      0.321874,
      "nf "
    ],
    [
      0.654655,
      "\r\n"
    ],
    [
      0.001527,
      "[main]"
    ],
    [
      0.000034,
      "\r\n"
    ],
    [
      0.000032,
      "cachedir=/var/cache/yum/$basearch/$releasever"
    ],
    [
      0.000025,
      "\r\n"
    ],
    [
      0.000033,
      "keepcache=0"
    ],
    [
      0.000019,
      "\r\n"
    ],
    [
      0.000024,
      "debuglevel=2"
    ],
    [
      0.000036,
      "\r\n"
    ],
    [
      0.000026,
      "logfile=/var/log/yum.log"
    ],
    [
      0.000019,
      "\r\n"
    ],
    [
      0.000038,
      "exactarch=1"
    ],
    [
      0.000019,
      "\r\n"
    ],
    [
      0.000037,
      "obsoletes=1"
    ],
    [
      0.000036,
      "\r\n"
    ],
    [
      0.000023,
      "gpgcheck=1"
    ],
    [
      0.000019,
      "\r\n"
    ],
    [
      0.000054,
      "plugins=1"
    ],
    [
      0.000018,
      "\r\n"
    ],
    [
      0.000059,
      "installonly_limit=5"
    ],
    [
      0.000019,
      "\r\n"
    ],
    [
      0.000054,
      "bugtracker_url=http://bugs.centos.org/set_project.php?project_id=23\u0026ref=http://b"
    ],
    [
      0.000021,
      "\r\n"
    ],
    [
      0.000045,
      "ugs.centos.org/bug_report_page.php?category=yum"
    ],
    [
      0.000019,
      "\r\n"
    ],
    [
      0.000026,
      "distroverpkg=centos-release"
    ],
    [
      0.000033,
      "\r\n"
    ],
    [
      0.000030,
      "\r\n"
    ],
    [
      0.000024,
      "\r\n"
    ],
    [
      0.000059,
      "#  This is the default, if you make this bigger yum won't see if the metadata"
    ],
    [
      0.000019,
      "\r\n"
    ],
    [
      0.000068,
      "# is newer on the remote and so you'll \"gain\" the bandwidth of not having to"
    ],
    [
      0.000019,
      "\r\n"
    ],
    [
      0.000057,
      "# download the new metadata and \"pay\" for it by yum not having correct"
    ],
    [
      0.000019,
      "\r\n"
    ],
    [
      0.000027,
      "# information."
    ],
    [
      0.000028,
      "\r\n"
    ],
    [
      0.000044,
      "#  It is esp. important, to have correct metadata, for distributions like"
    ],
    [
      0.000061,
      "\r\n"
    ],
    [
      0.000037,
      "# Fedora which don't keep old packages around. If you don't like this checking"
    ],
    [
      0.000054,
      "\r\n"
    ],
    [
      0.000036,
      "# interupting your command line usage, it's much better to have something"
    ],
    [
      0.000041,
      "\r\n"
    ],
    [
      0.000036,
      "# manually check the metadata once an hour (yum-updatesd will do this)."
    ],
    [
      0.000046,
      "\r\n"
    ],
    [
      0.000259,
      "\u001b[7m--More--(89%)\u001b[27m"
    ],
    [
      2.140198,
      "\r# metadata_expire=90m\r\n\r\n# PUT YOUR REPOS HERE OR IN separate files named file.repo\r\n# in /etc/yum.repos.d\r\n"
    ],
    [
      0.000374,
      "\u001b]0;grossp@localhost:~\u0007[grossp@~ ]\u003e "
    ],
    [
      4.503150,
      "#"
    ],
    [
      1.839902,
      "t"
    ],
    [
      0.096006,
      "o"
    ],
    [
      0.079982,
      " "
    ],
    [
      0.191890,
      "p"
    ],
    [
      0.072077,
      "a"
    ],
    [
      0.080039,
      "g"
    ],
    [
      0.111948,
      "e"
    ],
    [
      0.104029,
      " "
    ],
    [
      0.103983,
      "d"
    ],
    [
      0.047630,
      "o"
    ],
    [
      0.128389,
      "w"
    ],
    [
      0.111992,
      "n"
    ],
    [
      0.103873,
      " "
    ],
    [
      0.184126,
      "j"
    ],
    [
      0.167958,
      "u"
    ],
    [
      0.088048,
      "s"
    ],
    [
      0.079938,
      "t"
    ],
    [
      0.071987,
      " "
    ],
    [
      0.096029,
      "u"
    ],
    [
      0.095987,
      "s"
    ],
    [
      0.055980,
      "e"
    ],
    [
      0.103989,
      " "
    ],
    [
      0.079990,
      "t"
    ],
    [
      0.071879,
      "h"
    ],
    [
      0.111959,
      "e"
    ],
    [
      0.096161,
      " "
    ],
    [
      0.232003,
      "s"
    ],
    [
      0.063971,
      "p"
    ],
    [
      0.096018,
      "a"
    ],
    [
      0.096071,
      "c"
    ],
    [
      0.095993,
      "e"
    ],
    [
      0.119915,
      " "
    ],
    [
      0.119803,
      "b"
    ],
    [
      0.192220,
      "a"
    ],
    [
      0.215966,
      "r"
    ],
    [
      0.319959,
      ","
    ],
    [
      0.064045,
      " "
    ],
    [
      0.215740,
      "n"
    ],
    [
      0.120224,
      "o"
    ],
    [
      0.111997,
      " "
    ],
    [
      0.103956,
      "n"
    ],
    [
      0.135840,
      "e"
    ],
    [
      0.144185,
      "e"
    ],
    [
      0.191984,
      "d"
    ],
    [
      0.103968,
      " "
    ],
    [
      0.087868,
      "t"
    ],
    [
      0.072158,
      "o"
    ],
    [
      0.087962,
      " "
    ],
    [
      0.112014,
      "p"
    ],
    [
      0.104011,
      "r"
    ],
    [
      0.088007,
      "e"
    ],
    [
      0.199800,
      "s"
    ],
    [
      0.144146,
      "s"
    ],
    [
      0.239998,
      " "
    ],
    [
      0.152004,
      "q"
    ],
    [
      0.263964,
      ","
    ],
    [
      0.095980,
      " "
    ],
    [
      0.648436,
      "\r\n\u001b]0;grossp@localhost:~\u0007[grossp@~ ]\u003e "
    ],
    [
      0.319436,
      "#"
    ],
    [
      0.152063,
      "m"
    ],
    [
      0.159897,
      "o"
    ],
    [
      0.048009,
      "r"
    ],
    [
      0.056002,
      "e"
    ],
    [
      0.120023,
      " "
    ],
    [
      0.335983,
      "e"
    ],
    [
      0.240016,
      "x"
    ],
    [
      0.071970,
      "i"
    ],
    [
      0.159908,
      "t"
    ],
    [
      0.176110,
      "s"
    ],
    [
      0.103981,
      " "
    ],
    [
      0.119986,
      "a"
    ],
    [
      0.655947,
      "u"
    ],
    [
      0.143997,
      "t"
    ],
    [
      0.103984,
      "o"
    ],
    [
      0.199978,
      "m"
    ],
    [
      0.175999,
      "a"
    ],
    [
      0.200012,
      "t"
    ],
    [
      0.111985,
      "i"
    ],
    [
      0.127721,
      "c"
    ],
    [
      0.056284,
      "a"
    ],
    [
      0.071868,
      "l"
    ],
    [
      0.136126,
      "l"
    ],
    [
      0.031988,
      "y"
    ],
    [
      0.120100,
      " "
    ],
    [
      0.119471,
      "f"
    ],
    [
      0.047926,
      "o"
    ],
    [
      0.128462,
      "r"
    ],
    [
      0.072007,
      " "
    ],
    [
      0.151979,
      "y"
    ],
    [
      0.031591,
      "o"
    ],
    [
      0.104017,
      "u"
    ],
    [
      0.328391,
      "."
    ],
    [
      0.264373,
      "\r\n\u001b]0;grossp@localhost:~\u0007[grossp@~ ]\u003e "
    ],
    [
      0.647520,
      "#"
    ],
    [
      1.511896,
      "T"
    ],
    [
      0.800027,
      "\u0008\u001b[K"
    ],
    [
      0.095912,
      "r"
    ],
    [
      0.096034,
      "e"
    ],
    [
      0.223766,
      "c"
    ],
    [
      0.064200,
      "a"
    ],
    [
      0.104082,
      "l"
    ],
    [
      0.127926,
      "l"
    ],
    [
      0.151963,
      ":"
    ],
    [
      0.120023,
      " "
    ],
    [
      0.399818,
      "L"
    ],
    [
      0.264112,
      "E"
    ],
    [
      0.472055,
      "\u0008\u001b[K"
    ],
    [
      0.143956,
      "\u0008\u001b[K"
    ],
    [
      0.239579,
      "\""
    ],
    [
      0.232151,
      "L"
    ],
    [
      0.264203,
      "e"
    ],
    [
      0.223971,
      "s"
    ],
    [
      0.143821,
      "s"
    ],
    [
      0.104153,
      " "
    ],
    [
      0.103943,
      "i"
    ],
    [
      0.080071,
      "s"
    ],
    [
      0.072023,
      " "
    ],
    [
      0.095989,
      "m"
    ],
    [
      0.167968,
      "o"
    ],
    [
      0.047800,
      "r"
    ],
    [
      0.048013,
      "e"
    ],
    [
      0.160196,
      ","
    ],
    [
      0.072016,
      " "
    ],
    [
      0.319965,
      "m"
    ],
    [
      0.151976,
      "o"
    ],
    [
      0.071971,
      "r"
    ],
    [
      0.056057,
      "e"
    ],
    [
      0.095980,
      " "
    ],
    [
      0.111998,
      "i"
    ],
    [
      0.271746,
      "s"
    ],
    [
      0.128217,
      " "
    ],
    [
      0.143985,
      "l"
    ],
    [
      0.087915,
      "e"
    ],
    [
      0.224114,
      "s"
    ],
    [
      0.143970,
      "s"
    ],
    [
      0.255985,
      "\""
    ],
    [
      1.880320,
      "\r\n\u001b]0;grossp@localhost:~\u0007[grossp@~ ]\u003e "
    ],
    [
      0.231543,
      "#"
    ],
    [
      0.255969,
      "b"
    ],
    [
      0.191982,
      "a"
    ],
    [
      0.080018,
      "s"
    ],
    [
      0.135923,
      "i"
    ],
    [
      0.064040,
      "c"
    ],
    [
      0.055951,
      "a"
    ],
    [
      0.095784,
      "l"
    ],
    [
      0.136236,
      "l"
    ],
    [
      0.095991,
      "y"
    ],
    [
      0.128014,
      ","
    ],
    [
      0.079995,
      " "
    ],
    [
      0.151984,
      "u"
    ],
    [
      0.056048,
      "s"
    ],
    [
      0.063870,
      "e"
    ],
    [
      0.096074,
      " "
    ],
    [
      0.128000,
      "l"
    ],
    [
      0.095857,
      "e"
    ],
    [
      0.200010,
      "s"
    ],
    [
      0.152142,
      "s"
    ],
    [
      0.071716,
      " "
    ],
    [
      0.096219,
      "a"
    ],
    [
      0.088045,
      "s"
    ],
    [
      0.119976,
      " "
    ],
    [
      0.079984,
      "i"
    ],
    [
      0.087976,
      "t"
    ],
    [
      0.071602,
      " "
    ],
    [
      0.104364,
      "i"
    ],
    [
      0.128028,
      "s"
    ],
    [
      0.056022,
      " "
    ],
    [
      0.143943,
      "b"
    ],
    [
      0.360021,
      "e"
    ],
    [
      0.247837,
      "t"
    ],
    [
      0.168164,
      "t"
    ],
    [
      0.152080,
      "e"
    ],
    [
      0.087799,
      "r"
    ],
    [
      0.752073,
      "."
    ],
    [
      0.696328,
      "\r\n\u001b]0;grossp@localhost:~\u0007[grossp@~ ]\u003e "
    ],
    [
      1.111636,
      "\r\n\u001b]0;grossp@localhost:~\u0007[grossp@~ ]\u003e "
    ],
    [
      0.335820,
      "e"
    ],
    [
      0.263990,
      "x"
    ],
    [
      0.103899,
      "i"
    ],
    [
      0.160076,
      "t"
    ],
    [
      0.464633,
      "\r\nexit\r\n"
    ]
  ]
}