{"ID":23701,"Author":{"Name":"amriunix","ID":0,"FullName":"","Gravatar":"4cafbdfe5412a50a66823a93687d4721"},"Title":"Git and Github Tutorial - Part 7","Description":"\u003cdiv class=\"content\"\u003e\u003cp\u003eHi, Today in iThePro we will learn how to use Git and how to use with Github to build software and develop it. In this part we will see how to using the ignore file. - See more at: \u003ca href=\"http://www.ithepro.com/2015/07/git-and-github-tutorial-part-7.html#sthash.EYRQJh2K.dpuf\"\u003ehttp://www.ithepro.com/2015/07/git-and-github-tutorial-part-7.html#sthash.EYRQJh2K.dpuf\u003c/a\u003e\u003c/p\u003e\n\u003c/div\u003e","Time":"2015-07-21T09:29:00Z","Tags":["Linux","bash","xterm"]}